setup.py
redis_triplestore/__init__.py
redis_triplestore.egg-info/PKG-INFO
redis_triplestore.egg-info/SOURCES.txt
redis_triplestore.egg-info/dependency_links.txt
redis_triplestore.egg-info/top_level.txt