Metadata-Version: 1.0
Name: redis-triplestore
Version: 0.1
Summary: Implements a triplestore using Redis to store relations, in Python.
Home-page: http://code.welldev.org/redis_triplestore/
Author: David Larlet
Author-email: david@larlet.fr
License: BSD
Download-URL: http://code.welldev.org/redis_triplestore/downloads/
Keywords: redis triplestore
Platform: Any
Classifier: Development Status :: 3 - Alpha
Classifier: Intended Audience :: Developers
Classifier: License :: OSI Approved :: BSD License
Classifier: Operating System :: OS Independent
Classifier: Programming Language :: Python
Classifier: Topic :: Software Development :: Libraries :: Python Modules
